<?xml version="1.0" encoding="utf-8"?>
<XnaContent>
  <Asset Type="Vlak.Model.Level">
    <Number>13</Number>
    <Password>IDEAL</Password>
    <LevelMap>
      99  99  99  99  99  99  99  99  99  99  99  99  99  99  99  99  99  99  99  99
      99  99   9   9  99  99   0   0   0   0   0   0   0   0   0   0   0   4   4  99
      99  99   9   9   9  99   0   0   0  13   0   0   0   0   0   0   0   4   4  99
      99  99   9   9   9  99   0   0  13   0  13   0   0   0   0   0   0  99  99  99
      99  99  99   9   9  99   0   0   0  13   0   8   3   2   0   0   0   0   0  99
      99  23   0   0   0   0   0   0   0   0   5   3  99  99   0   1   0   0   0  99
      99   0   0   0   0   0   0   0   8   3  99  99  99   0   0   0   0   0   0  99
      99   0   0   0   0   0   5   3  99  99  99   1   0   1   0   0   0   0  10  99
      99   0   0   0   8   3  99  99  99   1   0   0   0   0   0   0   0  99  99  99
      99   0   0   3  99  99  99   1   0   0   1   0   1   0   1   0   0   4   4  99
      99   0   5  99  99   0   0   0   1   0   0   0  12  12  12   0   0   4   4  99
      99  99  99  99  99  99  99  50  99  99  99  99  99  99  99  99  99  99  99  99
    </LevelMap>
  </Asset>
</XnaContent>